runway/__init__.py
runway/errors.py
runway/logs.py
runway/main.py
runway/pytypes.py
runway/sdks/__init__.py
runway/sdks/openai.py
runway_sdk-0.1.2.dist-info/licenses/LICENSE
runway_sdk-0.1.2.dist-info/METADATA
runway_sdk-0.1.2.dist-info/WHEEL
runway_sdk-0.1.2.dist-info/top_level.txt
runway_sdk-0.1.2.dist-info/RECORD
